ipypopout/__init__.py
ipypopout/_version.py
ipypopout/popout_button.py
ipypopout/popout_button.vue
ipypopout-2.0.1.data/data/share/jupyter/voila/templates/ipypopout/static/popout.html
ipypopout-2.0.1.data/data/share/jupyter/voila/templates/ipypopout/static/popout.js
ipypopout-2.0.1.dist-info/LICENSE
ipypopout-2.0.1.dist-info/METADATA
ipypopout-2.0.1.dist-info/WHEEL
ipypopout-2.0.1.dist-info/top_level.txt
ipypopout-2.0.1.dist-info/RECORD
