Metadata-Version: 2.1
Name: ipypopout
Version: 2.0.1
Home-page: https://github.com/mariobuikhuizen/ipypopout
Author: Mario Buikhuizen
Author-email: mariobuikhuizen@gmail.com
License-File: LICENSE
Requires-Dist: ipywidgets>=7.7
Requires-Dist: ipyvuetify<2,>=1.7.0
Provides-Extra: solara
Requires-Dist: solara-server>=1.40.0; extra == "solara"
Provides-Extra: test
Requires-Dist: solara[pytest]; extra == "test"
Provides-Extra: voila
Requires-Dist: voila<0.5,>=0.2.10; extra == "voila"
